LICENSE.txt
README.rst
setup.cfg
setup.py
pywebloader/__init__.py
pywebloader.egg-info/PKG-INFO
pywebloader.egg-info/SOURCES.txt
pywebloader.egg-info/dependency_links.txt
pywebloader.egg-info/top_level.txt