Metadata-Version: 2.1
Name: pywebloader
Version: 1.3.1
Summary: Improves work with web files downloading.
Home-page: https://github.com/xzripper/PyLoader
Download-URL: https://github.com/xzripper/PyLoader/archive/refs/tags/v1.3.1.tar.gz
Author: Ivan Perzhinsky.
Author-email: name1not1found.com@gmail.com
License: MIT
Keywords: utility
Classifier: Development Status :: 5 - Production/Stable
Classifier: Intended Audience :: Developers
Classifier: Topic :: Utilities
Classifier: License :: OSI Approved :: MIT License
Classifier: Programming Language :: Python :: 3
License-File: LICENSE.txt
